python_motion_planning/__init__.py
python_motion_planning/curve_generation/__init__.py
python_motion_planning/curve_generation/bezier_curve.py
python_motion_planning/curve_generation/bspline_curve.py
python_motion_planning/curve_generation/cubic_spline.py
python_motion_planning/curve_generation/curve.py
python_motion_planning/curve_generation/dubins_curve.py
python_motion_planning/curve_generation/fem_pos_smooth.py
python_motion_planning/curve_generation/polynomial_curve.py
python_motion_planning/curve_generation/reeds_shepp.py
python_motion_planning/global_planner/__init__.py
python_motion_planning/global_planner/evolutionary_search/__init__.py
python_motion_planning/global_planner/evolutionary_search/aco.py
python_motion_planning/global_planner/evolutionary_search/evolutionary_search.py
python_motion_planning/global_planner/evolutionary_search/pso.py
python_motion_planning/global_planner/graph_search/__init__.py
python_motion_planning/global_planner/graph_search/a_star.py
python_motion_planning/global_planner/graph_search/d_star.py
python_motion_planning/global_planner/graph_search/d_star_lite.py
python_motion_planning/global_planner/graph_search/dijkstra.py
python_motion_planning/global_planner/graph_search/gbfs.py
python_motion_planning/global_planner/graph_search/graph_search.py
python_motion_planning/global_planner/graph_search/jps.py
python_motion_planning/global_planner/graph_search/lazy_theta_star.py
python_motion_planning/global_planner/graph_search/lpa_star.py
python_motion_planning/global_planner/graph_search/s_theta_star.py
python_motion_planning/global_planner/graph_search/theta_star.py
python_motion_planning/global_planner/graph_search/voronoi.py
python_motion_planning/global_planner/sample_search/__init__.py
python_motion_planning/global_planner/sample_search/informed_rrt.py
python_motion_planning/global_planner/sample_search/rrt.py
python_motion_planning/global_planner/sample_search/rrt_connect.py
python_motion_planning-1.1.1.dist-info/licenses/LICENSE
python_motion_planning-1.1.1.dist-info/METADATA
python_motion_planning-1.1.1.dist-info/WHEEL
python_motion_planning-1.1.1.dist-info/top_level.txt
python_motion_planning-1.1.1.dist-info/RECORD
