Metadata-Version: 2.4
Name: python-motion-planning
Version: 1.1.1
Summary: Motion planning algorithms for Python
Maintainer-email: Yang Haodong <913982779@qq.com>, Wu Maojia <2223942063@qq.com>
License: GNU GENERAL PUBLIC LICENSE
Project-URL: Repository, https://github.com/ai-winter/python_motion_planning
Classifier: License :: OSI Approved :: GNU General Public License v3 (GPLv3)
Classifier: Programming Language :: Python :: 3
Classifier: Programming Language :: Python :: 3 :: Only
Requires-Python: >=3.6
License-File: LICENSE
Requires-Dist: numpy
Requires-Dist: scipy
Requires-Dist: matplotlib
Requires-Dist: cvxopt
Requires-Dist: osqp
Requires-Dist: tqdm
Dynamic: license-file
